pyfitterbap/__init__.py
pyfitterbap/__main__.py
pyfitterbap/crc.cp39-win_amd64.pyd
pyfitterbap/pubsub.py
pyfitterbap/time.py
pyfitterbap/version.py
pyfitterbap/comm/__init__.py
pyfitterbap/comm/comm.cp39-win_amd64.pyd
pyfitterbap/comm/test/__init__.py
pyfitterbap/comm/ui/__init__.py
pyfitterbap/comm/ui/device_widget.py
pyfitterbap/comm/ui/expanding_widget.py
pyfitterbap/comm/ui/log_widget.py
pyfitterbap/comm/ui/main.py
pyfitterbap/comm/ui/open.py
pyfitterbap/comm/ui/resync.py
pyfitterbap/comm/ui/vertical_scroll_area.py
pyfitterbap/comm/ui/waveform.py
pyfitterbap/entry_points/__init__.py
pyfitterbap/entry_points/comm_ui.py
pyfitterbap/entry_points/crc.py
pyfitterbap/test/__init__.py
pyfitterbap/test/test_pubsub.py
pyfitterbap-0.4.1.dist-info/LICENSE
pyfitterbap-0.4.1.dist-info/METADATA
pyfitterbap-0.4.1.dist-info/WHEEL
pyfitterbap-0.4.1.dist-info/entry_points.txt
pyfitterbap-0.4.1.dist-info/top_level.txt
pyfitterbap-0.4.1.dist-info/RECORD
