Metadata-Version: 2.1
Name: pyfitterbap
Version: 0.4.1
Summary: Fitterbap python bindings
Home-page: https://github.com/jetperch/fitterbap
Author: Jetperch LLC
Author-email: dev@jetperch.com
License: Apache 2.0
Project-URL: Bug Reports, https://github.com/jetperch/fitterbap/issues
Project-URL: Funding, https://www.joulescope.com
Project-URL: Twitter, https://twitter.com/joulescope
Project-URL: Source, https://github.com/jetperch/fitterbap
Keywords: fitterbap pubsub uart
Platform: UNKNOWN
Classifier: Development Status :: 4 - Beta
Classifier: Intended Audience :: Developers
Classifier: Intended Audience :: End Users/Desktop
Classifier: Intended Audience :: Science/Research
Classifier: License :: OSI Approved :: Apache Software License
Classifier: Operating System :: Microsoft :: Windows :: Windows 10
Classifier: Operating System :: Microsoft :: Windows :: Windows 8.1
Classifier: Operating System :: Microsoft :: Windows :: Windows 8
Classifier: Operating System :: Microsoft :: Windows :: Windows 7
Classifier: Operating System :: MacOS :: MacOS X
Classifier: Operating System :: POSIX :: Linux
Classifier: Programming Language :: Python
Classifier: Programming Language :: Python :: 3
Classifier: Programming Language :: Python :: 3.8
Classifier: Programming Language :: Python :: 3.9
Classifier: Programming Language :: Python :: Implementation :: CPython
Classifier: Topic :: Scientific/Engineering
Classifier: Topic :: Software Development :: Embedded Systems
Classifier: Topic :: Software Development :: Testing
Classifier: Topic :: Utilities
Requires-Python: ~=3.8
Requires-Dist: numpy (>=1.20)
Requires-Dist: psutil (>=1.12)
Requires-Dist: pyqtgraph
Requires-Dist: pyserial
Requires-Dist: PySide6 (>=6.1.0)
Requires-Dist: python-dateutil (>=2.7.3)
Requires-Dist: pyqtgraph (>=0.12)
Requires-Dist: pypiwin32 (>=223)
Provides-Extra: dev
Requires-Dist: check-manifest ; extra == 'dev'
Requires-Dist: coverage ; extra == 'dev'
Requires-Dist: Cython ; extra == 'dev'
Requires-Dist: wheel ; extra == 'dev'
Requires-Dist: sphinx ; extra == 'dev'
Requires-Dist: m2r ; extra == 'dev'
